dwsimopt/__init__.py
dwsimopt/py2dwsim.py
dwsimopt/sim_opt.py
dwsimopt/solve_sim_opt.py
dwsimopt/utils.py
dwsimopt/tests/__init__.py
dwsimopt/tests/test_interface.py
dwsimopt/tests/test_py2dwsim.py
dwsimopt/tests/test_sim_opt.py
dwsimopt/tests/test_solve_sim_opt.py
dwsimopt-0.2.0.dist-info/LICENSE
dwsimopt-0.2.0.dist-info/METADATA
dwsimopt-0.2.0.dist-info/WHEEL
dwsimopt-0.2.0.dist-info/top_level.txt
dwsimopt-0.2.0.dist-info/RECORD
