Metadata-Version: 2.1
Name: dwsimopt
Version: 0.2.0
Summary: DWSIM automation with python for chemical process simulation optimization
Home-page: http://https://github.com/lf-santos/dwsimopt
Author: Lucas F. Santos
Author-email: lfs.francisco.95@gmal.com
License: MIT
Classifier: Development Status :: 3 - Alpha
Classifier: License :: OSI Approved :: MIT License
Classifier: Programming Language :: Python :: 3 :: Only
Classifier: Programming Language :: Python :: 3.8
Classifier: Topic :: Scientific/Engineering
Classifier: Topic :: Scientific/Engineering :: Mathematics
License-File: LICENSE
Requires-Dist: numpy
Requires-Dist: scipy
Requires-Dist: scikit-opt
Requires-Dist: wheel
Requires-Dist: pythonnet (==2.5.2)
Requires-Dist: pywin32
Requires-Dist: matplotlib
Provides-Extra: dev
Requires-Dist: ipykernel ; extra == 'dev'
Requires-Dist: build ; extra == 'dev'
Requires-Dist: twine ; extra == 'dev'
Requires-Dist: sphinx ; extra == 'dev'
Requires-Dist: sphinx-rtd-theme ; extra == 'dev'
Requires-Dist: check-manifest ; extra == 'dev'
